osiotk/__init__.py
osiotk/constants.py
osiotk/objects.py
osiotk/path/__init__.py
osiotk/scan/__init__.py
osiotk-1.2.4.dist-info/WHEEL
osiotk-1.2.4.dist-info/METADATA
osiotk-1.2.4.dist-info/RECORD
